fmiweather/__init__.py
fmiweather-0.0.3.dist-info/DESCRIPTION.rst
fmiweather-0.0.3.dist-info/METADATA
fmiweather-0.0.3.dist-info/RECORD
fmiweather-0.0.3.dist-info/WHEEL
fmiweather-0.0.3.dist-info/metadata.json
fmiweather-0.0.3.dist-info/top_level.txt
