Metadata-Version: 2.0
Name: fmiweather
Version: 0.0.3
Summary: Fetches and parses weather information from fmi.fi
Home-page: https://github.com/ojarva/python-fmi-weather
Author: Olli Jarva
Author-email: olli@jarva.fi
License: BSD
Keywords: weather fmi
Platform: UNKNOWN
Classifier: Development Status :: 4 - Beta
Classifier: Intended Audience :: Developers
Classifier: License :: OSI Approved :: BSD License
Classifier: Programming Language :: Python :: 2.7
Requires-Dist: beautifulsoup4
Requires-Dist: requests
Provides-Extra: dev
Requires-Dist: twine; extra == 'dev'
Requires-Dist: wheel; extra == 'dev'
